wallex/__init__.py
wallex/_package_data.py
wallex/enums.py
wallex/exceptions.py
wallex/models.py
wallex/clients/__init__.py
wallex/clients/base.py
wallex/clients/main.py
wallex/wallex_deprecated/__init__.py
wallex/wallex_deprecated/_deprecated.py
wallex/wallex_deprecated/_package_data.py
wallex/wallex_deprecated/exceptions.py
wallex/wallex_deprecated/main.py
wallex/wallex_deprecated/websocket.py
wallex-0.5.2.dist-info/METADATA
wallex-0.5.2.dist-info/WHEEL
wallex-0.5.2.dist-info/top_level.txt
wallex-0.5.2.dist-info/RECORD
