Metadata-Version: 2.1
Name: wallex
Version: 0.5.2
Summary: Wallex cryptocurrency exchange python sdk
Home-page: https://github.com/amiwrpremium/wallex
Author: amiwrpremium
Author-email: amiwrpremium@gmail.com
License: MIT
Project-URL: Bug Tracker, https://github.com/amiwrpremium/wallex/issues
Keywords: wallex,crypto,exchange,API,SDK
Classifier: Development Status :: 3 - Alpha
Classifier: Intended Audience :: Developers
Classifier: Topic :: Software Development :: Build Tools
Classifier: License :: OSI Approved :: MIT License
Classifier: Programming Language :: Python :: 3
Classifier: Programming Language :: Python :: 3.4
Classifier: Programming Language :: Python :: 3.5
Classifier: Programming Language :: Python :: 3.6
Classifier: Programming Language :: Python :: 3.7
Classifier: Programming Language :: Python :: 3.8
Classifier: Programming Language :: Python :: 3.9
Requires-Python: >=3.6
Requires-Dist: requests
Requires-Dist: simplejson
Requires-Dist: deprecation
Requires-Dist: python-socketio (==4.6.1)
Requires-Dist: python-engineio (==3.14.2)
Requires-Dist: websocket-client (==1.3.2)
Requires-Dist: aiohttp[speedups]
Requires-Dist: pydantic
